safemotions/__init__.py
safemotions/evaluate.py
safemotions/random_agent.py
safemotions/train.py
safemotions/description/meshes/iiwa7/collision/base.stl
safemotions/description/meshes/iiwa7/collision/link1.stl
safemotions/description/meshes/iiwa7/collision/link2.stl
safemotions/description/meshes/iiwa7/collision/link3.stl
safemotions/description/meshes/iiwa7/collision/link4.stl
safemotions/description/meshes/iiwa7/collision/link5.stl
safemotions/description/meshes/iiwa7/collision/link6.stl
safemotions/description/meshes/iiwa7/collision/link7.stl
safemotions/description/meshes/iiwa7/visual/base.dae
safemotions/description/meshes/iiwa7/visual/link1.dae
safemotions/description/meshes/iiwa7/visual/link2.dae
safemotions/description/meshes/iiwa7/visual/link3.dae
safemotions/description/meshes/iiwa7/visual/link4.dae
safemotions/description/meshes/iiwa7/visual/link5.dae
safemotions/description/meshes/iiwa7/visual/link6.dae
safemotions/description/meshes/iiwa7/visual/link7.dae
safemotions/description/meshes/misc/visual/base_adapter.dae
safemotions/description/meshes/misc/visual/table.dae
safemotions/description/meshes/obstacles/collision/monitor_no_pivot.obj
safemotions/description/meshes/obstacles/collision/monitor_pivot.obj
safemotions/description/meshes/obstacles/visual/monitor_no_pivot.obj
safemotions/description/meshes/obstacles/visual/monitor_pivot.obj
safemotions/description/urdf/one_robot.urdf
safemotions/description/urdf/three_robots.urdf
safemotions/description/urdf/two_robots.urdf
safemotions/description/urdf/obstacles/monitor_no_pivot.urdf
safemotions/description/urdf/obstacles/monitor_pivot.urdf
safemotions/envs/__init__.py
safemotions/envs/safe_motions_base.py
safemotions/envs/safe_motions_env.py
safemotions/envs/decorators/__init__.py
safemotions/envs/decorators/actions.py
safemotions/envs/decorators/observations.py
safemotions/envs/decorators/rewards.py
safemotions/envs/decorators/video_recording.py
safemotions/model/__init__.py
safemotions-1.0.1.dist-info/LICENSE
safemotions-1.0.1.dist-info/METADATA
safemotions-1.0.1.dist-info/WHEEL
safemotions-1.0.1.dist-info/top_level.txt
safemotions-1.0.1.dist-info/RECORD
