Metadata-Version: 2.1
Name: safemotions
Version: 1.0.1
Summary: Learning Collision-free and Torque-limited Robot Trajectories based on Alternative Safe Behaviors.
Home-page: https://github.com/translearn/safemotions
Author: Jonas C. Kiemel
Author-email: jonas.kiemel@kit.edu
License: MIT
Platform: UNKNOWN
Classifier: License :: OSI Approved :: MIT License
Classifier: Intended Audience :: Developers
Classifier: Programming Language :: Python :: 3.6
Classifier: Programming Language :: Python :: 3.7
Classifier: Programming Language :: Python :: 3.8
Classifier: Programming Language :: Python :: 3.9
Requires-Python: >=3.5
License-File: LICENSE
Requires-Dist: numpy
Requires-Dist: klimits (>=1.1.1)
Requires-Dist: matplotlib
Requires-Dist: pybullet
Requires-Dist: gym
Requires-Dist: Pillow
Provides-Extra: train
Requires-Dist: aioredis (==1.3.1) ; extra == 'train'
Requires-Dist: ray[default] (==1.4.1) ; extra == 'train'
Requires-Dist: ray[rllib] (==1.4.1) ; extra == 'train'
Requires-Dist: tensorflow ; extra == 'train'
